quadexpo/__init__.py
quadexpo-1.5.0.dist-info/METADATA
quadexpo-1.5.0.dist-info/WHEEL
quadexpo-1.5.0.dist-info/top_level.txt
quadexpo-1.5.0.dist-info/RECORD
